check_pam/__init__.py
check_pam/__main__.py
check_pam-0.2.1.data/scripts/check_pam
pamtester/__init__.py
check_pam-0.2.1.dist-info/LICENSE
check_pam-0.2.1.dist-info/METADATA
check_pam-0.2.1.dist-info/WHEEL
check_pam-0.2.1.dist-info/top_level.txt
check_pam-0.2.1.dist-info/RECORD
