Metadata-Version: 2.1
Name: check_pam
Version: 0.2.1
Summary: check_pam is an Icinga2/Nagios plugin which uses `pamtester` to test PAM operations
Home-page: https://github.com/theias/check_pam
Author: Christopher Peterson
Author-email: 
Project-URL: Documentation, https://github.com/theias/check_pam
Project-URL: Bug Tracker, https://github.com/theias/check_pam/issues
Project-URL: Source, https://github.com/theias/check_pam
Classifier: Programming Language :: Python :: 3
Classifier: License :: OSI Approved :: MIT License
Classifier: Operating System :: OS Independent
Requires-Python: >=3.6
License-File: LICENSE
Requires-Dist: nagiosplugin<2.0.0,>=1.3.3
